utf8convert/__init__.py
utf8convert/cli.py
utf8convert-0.2.0.dist-info/METADATA
utf8convert-0.2.0.dist-info/WHEEL
utf8convert-0.2.0.dist-info/entry_points.txt
utf8convert-0.2.0.dist-info/licenses/LICENSE
utf8convert-0.2.0.dist-info/RECORD
