Metadata-Version: 2.4
Name: utf8convert
Version: 0.2.0
Summary: A CLI tool to convert files (.cpp, .h, etc.) to UTF-8 encoding.
Project-URL: Homepage, https://github.com/yhbyhb/utf8convert
Project-URL: Repository, https://github.com/yhbyhb/utf8convert
Project-URL: Issues, https://github.com/yhbyhb/utf8convert/issues
Author-email: HanByul Yang <hanbyul.yang@gmail.com>
License: MIT License
License-File: LICENSE
Requires-Python: >=3.7
Requires-Dist: chardet
Requires-Dist: rich
Requires-Dist: typer
